[

  {
    "id": 1,
    "name": "Криштиану Роналду",
    "email": "cristiano@cr7",
    "phone": "+791145678921",
    "purchases": [
      {"id": 1, "date": "2025-05-11"},
      {"id": 4, "date": "2025-05-13"},
      {"id": 6, "date": "2025-05-16"},
      {"id": 7, "date": "2025-05-17"}
    ]
  },
  {
    "id": 2,
    "name": "Неймар",
    "email": "neymarjr@ney10",
    "phone": "+79114103465",
    "purchases": [
      {"id": 1, "date": "2025-05-11"},
      {"id": 4, "date": "2025-05-17"},
      {"id": 6, "date": "2025-05-18"},
      {"id": 7, "date": "2025-05-19"}
    ]
  }
]
